ddim/__init__.py
ddim/forward_ddim.py
ddim/reverse_ddim.py
ddim/sample_ddim.py
ddim/scheduler.py
ddim/test_ddim.py
ddim/train_ddim.py
ddpm/__init__.py
ddpm/forward_ddpm.py
ddpm/reverse_ddpm.py
ddpm/sample_ddpm.py
ddpm/scheduler.py
ddpm/test_ddpm.py
ddpm/train_ddpm.py
ldm/__init__.py
ldm/autoencoder.py
ldm/sample_ldm.py
ldm/train_autoencoder.py
ldm/train_ldm.py
sde/__init__.py
sde/forward_sde.py
sde/reverse_sde.py
sde/sample_sde.py
sde/scheduler.py
sde/test_sde.py
sde/train_sde.py
torchdiff/__init__.py
torchdiff/ddim.py
torchdiff/ddpm.py
torchdiff/ldm.py
torchdiff/sde.py
torchdiff/unclip.py
torchdiff/utils.py
torchdiff/tests/__init__.py
torchdiff/tests/test_ddim.py
torchdiff/tests/test_ddpm.py
torchdiff/tests/test_sde.py
torchdiff-2.3.0.dist-info/licenses/LICENSE
unclip/__init__.py
unclip/clip_encoder.py
unclip/forward_unclip.py
unclip/projections.py
unclip/reverse_unclip.py
unclip/scheduler.py
unclip/train_unclip_decoder.py
unclip/train_unclip_prior.py
unclip/unclip_decoder.py
unclip/unclip_sampler.py
unclip/unclip_trainstormer_prior.py
unclip/upsampler_trainer.py
unclip/upsampler_unclip.py
utils/__init__.py
utils/diff_net.py
utils/losses.py
utils/metrics.py
utils/text_encoder.py
torchdiff-2.3.0.dist-info/METADATA
torchdiff-2.3.0.dist-info/WHEEL
torchdiff-2.3.0.dist-info/top_level.txt
torchdiff-2.3.0.dist-info/RECORD
