Metadata-Version: 2.4
Name: TorchDiff
Version: 2.3.0
Summary: A PyTorch-based library for diffusion models
Home-page: https://github.com/LoqmanSamani/TorchDiff
Author: Loghman Samani
Author-email: samaniloqman91@gmail.com
License: MIT
Project-URL: Homepage, https://loqmansamani.github.io/torchdiff
Project-URL: Documentation, https://torchdiff.readthedio
Project-URL: Source, https://github.com/LoqmanSamani/TorchDiff
Keywords: diffusion models,pytorch,machine learning,deep learning
Classifier: Programming Language :: Python :: 3.10
Classifier: Programming Language :: Python :: 3.11
Classifier: Programming Language :: Python :: 3.12
Classifier: License :: OSI Approved :: MIT License
Classifier: Operating System :: OS Independent
Classifier: Intended Audience :: Developers
Classifier: Intended Audience :: Science/Research
Classifier: Topic :: Scientific/Engineering :: Artificial Intelligence
Classifier: Topic :: Software Development :: Libraries :: Python Modules
Requires-Python: >=3.10
License-File: LICENSE
Requires-Dist: lpips>=0.1.4
Requires-Dist: pytorch-fid>=0.3.0
Requires-Dist: torch>=2.0.0
Requires-Dist: torchvision>=0.15.0
Requires-Dist: tqdm>=4.60.0
Requires-Dist: transformers>=4.20.0
Requires-Dist: torchmetrics>=1.0.0
Provides-Extra: test
Requires-Dist: pytest>=7.0.0; extra == "test"
Requires-Dist: pytest-cov>=4.0.0; extra == "test"
Provides-Extra: dev
Requires-Dist: black; extra == "dev"
Requires-Dist: flake8; extra == "dev"
Requires-Dist: mypy; extra == "dev"
Dynamic: author
Dynamic: author-email
Dynamic: classifier
Dynamic: description
Dynamic: description-content-type
Dynamic: home-page
Dynamic: keywords
Dynamic: license
Dynamic: license-file
Dynamic: project-url
Dynamic: provides-extra
Dynamic: requires-dist
Dynamic: requires-python
Dynamic: summary
